yachtcharter/__init__.py
yachtcharter/test.py
yachtcharter-1.0.5.dist-info/METADATA
yachtcharter-1.0.5.dist-info/WHEEL
yachtcharter-1.0.5.dist-info/top_level.txt
yachtcharter-1.0.5.dist-info/RECORD
